odoo/addons/product_supplierinfo_purchase_contact/README.rst
odoo/addons/product_supplierinfo_purchase_contact/__init__.py
odoo/addons/product_supplierinfo_purchase_contact/__manifest__.py
odoo/addons/product_supplierinfo_purchase_contact/i18n/es.po
odoo/addons/product_supplierinfo_purchase_contact/i18n/it.po
odoo/addons/product_supplierinfo_purchase_contact/i18n/product_supplierinfo_purchase_contact.pot
odoo/addons/product_supplierinfo_purchase_contact/models/__init__.py
odoo/addons/product_supplierinfo_purchase_contact/models/product_supplierinfo.py
odoo/addons/product_supplierinfo_purchase_contact/models/stock_rule.py
odoo/addons/product_supplierinfo_purchase_contact/readme/CONTEXT.md
odoo/addons/product_supplierinfo_purchase_contact/readme/CONTRIBUTORS.md
odoo/addons/product_supplierinfo_purchase_contact/readme/DESCRIPTION.md
odoo/addons/product_supplierinfo_purchase_contact/readme/USAGE.md
odoo/addons/product_supplierinfo_purchase_contact/static/description/icon.png
odoo/addons/product_supplierinfo_purchase_contact/static/description/index.html
odoo/addons/product_supplierinfo_purchase_contact/tests/__init__.py
odoo/addons/product_supplierinfo_purchase_contact/tests/test_stock_rule.py
odoo/addons/product_supplierinfo_purchase_contact/views/product_supplierinfo_view.xml
odoo_addon_product_supplierinfo_purchase_contact-18.0.1.0.0.2.dist-info/METADATA
odoo_addon_product_supplierinfo_purchase_contact-18.0.1.0.0.2.dist-info/WHEEL
odoo_addon_product_supplierinfo_purchase_contact-18.0.1.0.0.2.dist-info/top_level.txt
odoo_addon_product_supplierinfo_purchase_contact-18.0.1.0.0.2.dist-info/RECORD
